tradestation_api/__init__.py
tradestation_api/tradestation.py
tradestation_api-0.0.1.dist-info/METADATA
tradestation_api-0.0.1.dist-info/WHEEL
tradestation_api-0.0.1.dist-info/top_level.txt
tradestation_api-0.0.1.dist-info/RECORD
