Metadata-Version: 2.1
Name: tradestation-api
Version: 0.0.1
Summary: Unofficial Tradestation API wrapper in Python 3.
Home-page: https://github.com/itsjafer/tradestation-api
Author: Jafer Haider
Author-email: itsjafer@gmail.com
License: MIT
Download-URL: https://github.com/itsjafer/tradestation-api/tarball/master
Platform: UNKNOWN
Classifier: Development Status :: 3 - Alpha
Classifier: Intended Audience :: Developers
Classifier: Topic :: Software Development :: Build Tools
Classifier: License :: OSI Approved :: MIT License
Classifier: Programming Language :: Python :: 3.7
Classifier: Programming Language :: Python :: 3.8
Classifier: Programming Language :: Python :: 3.9
Requires-Dist: playwright
Requires-Dist: playwright-stealth
